{
  "$type": "Comindware.Platform.Contracts.FormModel, Comindware.Platform.Contracts",
  "GlobalAlias": {
    "$type": "Comindware.Platform.Contracts.GlobalAlias, Comindware.Platform.Contracts",
    "Type": "CaseForm",
    "Owner": "df",
    "Alias": "df_CaseForm"
  },
  "IsDefault": false,
  "Root": {
    "$type": "Comindware.Platform.Contracts.VerticalLayoutModel, Comindware.Platform.Contracts",
    "GlobalAlias": {
      "$type": "Comindware.Platform.Contracts.GlobalAlias, Comindware.Platform.Contracts",
      "Type": "FormComponent",
      "Alias": "case_Root"
    },
    "AccessType": "Undefined",
    "Width": 0,
    "Type": "VerticalLayout"
  },
  "Name": "df - Основная форма",
  "Origination": "Undefined"
}