{
  "$type": "Comindware.Platform.Contracts.FlowActivityModel, Comindware.Platform.Contracts",
  "GlobalAlias": {
    "$type": "Comindware.Platform.Contracts.GlobalAlias, Comindware.Platform.Contracts",
    "Type": "Activity",
    "Owner": "Zakazavtotransporta",
    "Alias": "executionFlow3"
  },
  "TargetActivity": {
    "$type": "Comindware.Platform.Contracts.ConnectorModel, Comindware.Platform.Contracts",
    "Target": {
      "$type": "Comindware.Platform.Contracts.GlobalAlias, Comindware.Platform.Contracts",
      "Type": "Activity",
      "Owner": "Zakazavtotransporta",
      "Alias": "exclusiveGate1"
    },
    "TargetConnectorIndex": 30
  },
  "SourceActivity": {
    "$type": "Comindware.Platform.Contracts.ConnectorModel, Comindware.Platform.Contracts",
    "Target": {
      "$type": "Comindware.Platform.Contracts.GlobalAlias, Comindware.Platform.Contracts",
      "Type": "Activity",
      "Owner": "Zakazavtotransporta",
      "Alias": "userTask1"
    },
    "TargetConnectorIndex": 40
  },
  "Points": {
    "$type": "Comindware.Platform.Contracts.VectorModel[], Comindware.Platform.Contracts",
    "$values": [
      {
        "$type": "Comindware.Platform.Contracts.VectorModel, Comindware.Platform.Contracts",
        "X": -5.355190258574,
        "Y": -49.9546327837799
      },
      {
        "$type": "Comindware.Platform.Contracts.VectorModel, Comindware.Platform.Contracts",
        "X": 14.644809741426,
        "Y": -49.9546327837799
      },
      {
        "$type": "Comindware.Platform.Contracts.VectorModel, Comindware.Platform.Contracts",
        "X": 111.644809741426,
        "Y": -49.9546327837799
      },
      {
        "$type": "Comindware.Platform.Contracts.VectorModel, Comindware.Platform.Contracts",
        "X": 111.644809741426,
        "Y": -3.39118533635701
      },
      {
        "$type": "Comindware.Platform.Contracts.VectorModel, Comindware.Platform.Contracts",
        "X": 131.644809741426,
        "Y": -3.39118533635701
      }
    ]
  },
  "SequenceDefinition": {
    "$type": "Comindware.Platform.Contracts.SequenceFlowDefinitionModel, Comindware.Platform.Contracts",
    "IsDefault": false
  },
  "IsTitleSet": false,
  "Position": {
    "$type": "Comindware.Platform.Contracts.VectorModel, Comindware.Platform.Contracts",
    "X": 445.355190258574,
    "Y": 423.391185336357
  },
  "Size": {
    "$type": "Comindware.Platform.Contracts.DimensionsModel, Comindware.Platform.Contracts",
    "Width": 0.0,
    "Height": 0.0
  },
  "Owner": {
    "$type": "Comindware.Platform.Contracts.GlobalAlias, Comindware.Platform.Contracts",
    "Type": "Activity",
    "Owner": "Zakazavtotransporta",
    "Alias": "lane2"
  },
  "OwnerEmbeddedProcessActivityAlias": {
    "$type": "Comindware.Platform.Contracts.GlobalAlias, Comindware.Platform.Contracts",
    "Type": "Undefined"
  },
  "MountedOnAlias": {
    "$type": "Comindware.Platform.Contracts.GlobalAlias, Comindware.Platform.Contracts",
    "Type": "Undefined"
  },
  "Type": "ExecutionFlow"
}